gpsr/__init__.py
gpsr/_version.py
gpsr/analysis.py
gpsr/beams.py
gpsr/data_processing.py
gpsr/datasets.py
gpsr/diagnostics.py
gpsr/losses.py
gpsr/modeling.py
gpsr/train.py
gpsr/utils.py
gpsr/variational.py
gpsr/visualization.py
gpsr/custom_cheetah/__init__.py
gpsr/custom_cheetah/screen.py
gpsr/tests/test_beams.py
gpsr/tests/test_data_processing.py
gpsr/tests/test_datasets.py
gpsr/tests/test_diagnostics.py
gpsr/tests/test_modeling.py
gpsr/tests/test_visualization.py
gpsr-0.1.0.dist-info/METADATA
gpsr-0.1.0.dist-info/WHEEL
gpsr-0.1.0.dist-info/top_level.txt
gpsr-0.1.0.dist-info/RECORD
