Metadata-Version: 2.4
Name: gpsr
Version: 0.1.0
Summary: Phase space reconstruction using differentiable beam dynamics and generative beam representations
Author: Ryan Roussel, Juan Pablo Gonzalez Aguilera
Project-URL: Homepage, https://github.com/roussel-ryan/gpsr
Classifier: Development Status :: 4 - Beta
Classifier: Natural Language :: English
Classifier: Programming Language :: Python :: 3
Classifier: Topic :: Scientific/Engineering
Requires-Python: >=3.10
Requires-Dist: lightning
Requires-Dist: matplotlib
Requires-Dist: cheetah-accelerator>=0.7.1
Requires-Dist: tensorboard
Requires-Dist: scipy
Requires-Dist: scikit-image
Provides-Extra: dev
Requires-Dist: pytest; extra == "dev"
Requires-Dist: pytest-cov; extra == "dev"
Requires-Dist: jupyter; extra == "dev"
Requires-Dist: pre-commit; extra == "dev"
Provides-Extra: doc
Requires-Dist: mkdocs; extra == "doc"
Requires-Dist: mkdocs-jupyter; extra == "doc"
Requires-Dist: mkdocs-macros-plugin; extra == "doc"
Requires-Dist: mkdocs-material; extra == "doc"
Requires-Dist: mkdocstrings; extra == "doc"
Requires-Dist: mkdocstrings-python; extra == "doc"
